billots/__init__.py
billots/src/__init__.py
billots/src/controller/__init__.py
billots/src/controller/server.py
billots/src/controller/start.py
billots/src/controller/wallet.py
billots/src/mock/__init__.py
billots/src/mock/disputed_example.py
billots/src/mock/launch_servers.py
billots/src/model/__init__.py
billots/src/model/billot.py
billots/src/model/billots.py
billots/src/model/crypto.py
billots/src/model/db.py
billots/src/model/hosts.py
billots/src/model/notifications.py
billots/src/resources/trusted_hosts.json
billots/src/resources/trusted_test_hosts.json
billots/src/resources/values.json
billots/src/utils/__init__.py
billots/src/utils/socket_utils.py
billots/src/utils/utils.py
billots/tests/__init__.py
billots/tests/test_base.py
billots/tests/test_billot.py
billots/tests/test_billots.py
billots/tests/test_crypto.py
billots/tests/test_database.py
billots/tests/test_hosts.py
billots/tests/test_notifications.py
billots/tests/test_server.py
billots-0.1.1.dist-info/DESCRIPTION.rst
billots-0.1.1.dist-info/METADATA
billots-0.1.1.dist-info/RECORD
billots-0.1.1.dist-info/WHEEL
billots-0.1.1.dist-info/entry_points.txt
billots-0.1.1.dist-info/metadata.json
billots-0.1.1.dist-info/top_level.txt
