Metadata-Version: 2.0
Name: billots
Version: 0.1.1
Summary: Official project of billots.org cryptocurrency.
Home-page: https://github.com/billychasen/billots
Author: Billy Chasen
Author-email: billy@billychasen.com
License: MIT
Keywords: billots cryptocurrency billot
Platform: UNKNOWN
Requires-Python: >=3
Requires-Dist: Automat (==0.6.0)
Requires-Dist: Twisted (==17.5.0)
Requires-Dist: attrs (==17.2.0)
Requires-Dist: constantly (==15.1.0)
Requires-Dist: hyperlink (==17.2.1)
Requires-Dist: incremental (==17.5.0)
Requires-Dist: leveldb (==0.194)
Requires-Dist: py (==1.4.34)
Requires-Dist: pycrypto (==2.6.1)
Requires-Dist: pytest (==3.1.3)
Requires-Dist: six (==1.10.0)
Requires-Dist: zope.interface (==4.4.2)
